odoo/addons/fieldservice_agreement/README.rst
odoo/addons/fieldservice_agreement/__init__.py
odoo/addons/fieldservice_agreement/__manifest__.py
odoo/addons/fieldservice_agreement/i18n/de.po
odoo/addons/fieldservice_agreement/i18n/es.po
odoo/addons/fieldservice_agreement/i18n/es_AR.po
odoo/addons/fieldservice_agreement/i18n/es_CL.po
odoo/addons/fieldservice_agreement/i18n/fieldservice_agreement.pot
odoo/addons/fieldservice_agreement/i18n/pt_BR.po
odoo/addons/fieldservice_agreement/models/__init__.py
odoo/addons/fieldservice_agreement/models/agreement.py
odoo/addons/fieldservice_agreement/models/fsm_equipment.py
odoo/addons/fieldservice_agreement/models/fsm_location.py
odoo/addons/fieldservice_agreement/models/fsm_order.py
odoo/addons/fieldservice_agreement/models/fsm_person.py
odoo/addons/fieldservice_agreement/readme/CONFIGURE.rst
odoo/addons/fieldservice_agreement/readme/CONTRIBUTORS.rst
odoo/addons/fieldservice_agreement/readme/CREDITS.rst
odoo/addons/fieldservice_agreement/readme/DESCRIPTION.rst
odoo/addons/fieldservice_agreement/readme/ROADMAP.rst
odoo/addons/fieldservice_agreement/readme/USAGE.rst
odoo/addons/fieldservice_agreement/static/description/icon.png
odoo/addons/fieldservice_agreement/static/description/index.html
odoo/addons/fieldservice_agreement/tests/__init__.py
odoo/addons/fieldservice_agreement/tests/test_fsm_agreement.py
odoo/addons/fieldservice_agreement/views/agreement_view.xml
odoo/addons/fieldservice_agreement/views/fsm_equipment_view.xml
odoo/addons/fieldservice_agreement/views/fsm_location.xml
odoo/addons/fieldservice_agreement/views/fsm_order_view.xml
odoo/addons/fieldservice_agreement/views/fsm_person.xml
odoo14_addon_fieldservice_agreement-14.0.1.1.1.dist-info/METADATA
odoo14_addon_fieldservice_agreement-14.0.1.1.1.dist-info/WHEEL
odoo14_addon_fieldservice_agreement-14.0.1.1.1.dist-info/top_level.txt
odoo14_addon_fieldservice_agreement-14.0.1.1.1.dist-info/RECORD
